{
    "postNum": 9,
    "postUrl": "https://www.facebook.com/groups/403787519759673/posts/2104421179696290/",
    "postText": "·\nלהשכרה במיקום מושלם ליד כיכר המדינה, ברח' ז'בוטינסקי!\nדירת 4 חדרים גדולה, 120 מ\"ר.חדשה!!\n(רק סיימה שיפוץ יסודי, לא גרו בנכס)\nמוארת, סלון גדול לאירוח, מטבח בנפרד  \n3 חדרי שינה גדולים, עורפיים ושקטים (מזגן בכל חדר).\nקומה 3, מעלית + חניה (משותפת, יש מקום לכולם).\nשכר דירה: 12,000 ₪.\nארנונה - 1,100 ₪ לחודשיים \nועד בית -640 ₪ ש''ח \nבע''ח יתקבלו בברכה\nחוזה לשנה + אופציה לשנה נוספת\nבעל דירה מקסים!\nמושלמת למשפחה!!\nלפרטים נוספים ותיאום קל התקשרו עכשיו!\n050-8312961\nטונג'י נויין סוכנות יש נדל''ן \nואפשר פשוט להקליק על הקישור ולשלוח לי הודעת Whatsapp\nhttps://bit.ly/3oCklhP\n+5\n₪12,000\n  · תל אביב-יפו, תל אביב\n3 beds · 1 bath · Apartment/condo\nMessage\n",
    "isContainsPic": true,
    "stateArr": [
      {
        "state": "q0",
        "matchedWord": ""
      },
      {
        "state": "q15",
        "matchedWord": "ברח'"
      },
      {
        "state": "q0",
        "matchedWord": "ז'בוטינסקי!"
      },
      {
        "state": "q6",
        "matchedWord": "דירת"
      },
      {
        "state": "q1",
        "matchedWord": "4"
      },
      {
        "state": "q3",
        "matchedWord": "חדרים"
      },
      {
        "state": "q0",
        "matchedWord": "גדולה,"
      },
      {
        "state": "q1",
        "matchedWord": "3"
      },
      {
        "state": "q2",
        "matchedWord": "חדרי"
      },
      {
        "state": "q0",
        "matchedWord": "שינה"
      },
      {
        "state": "q12",
        "matchedWord": "חדר)."
      },
      {
        "state": "q0",
        "matchedWord": "קומה"
      },
      {
        "state": "q14",
        "matchedWord": "12,000"
      },
      {
        "state": "q0",
        "matchedWord": "₪."
      },
      {
        "state": "q14",
        "matchedWord": "1,100"
      },
      {
        "state": "q0",
        "matchedWord": "₪"
      },
      {
        "state": "q13",
        "matchedWord": "050-8312961"
      },
      {
        "state": "q0",
        "matchedWord": "טונג'י"
      },
      {
        "state": "q14",
        "matchedWord": "₪12,000"
      },
      {
        "state": "q0",
        "matchedWord": "·"
      },
      {
        "state": "q1",
        "matchedWord": "3"
      },
      {
        "state": "q0",
        "matchedWord": "·"
      },
      {
        "state": "q1",
        "matchedWord": "1"
      },
      {
        "state": "q0",
        "matchedWord": "·"
      }
    ],
    "rooms": [
      "4"
    ],
    "price": [
      "12,000",
      "1,100",
      "₪12,000"
    ],
    "street": [
      "ז'בוטינסקי!"
    ],
    "phone": [
      "050-8312961"
    ],
    "roommate": [],
    "femaleRoommate": [],
    "maleRoommate": [],
    "sablet": [],
    "studio": [],
    "unit": [],
    "similarStreets": [
      "ז'בוטינסקי",
      "הקישון"
    ]
  }